{
    "last_updated": "2025-05-23T07:26:54.726553",
    "deals": [
        {
            "category": "Appliances",
            "title": "De'Longhi - Digital All - in - One Combination Coffee and Espresso Machine - Black and Stainless Steel",
            "sku": "6422017",
            "price": 379.95,
            "savings": 80.0,
            "discount_percent": 21.055402026582446,
            "priority_score": 503.755980410613,
            "reviews": 743,
            "image_url": "images/6422017.jpg"
        },
        {
            "category": "Appliances",
            "title": "Samsung - Bespoke 29 Cu. Ft. 4 - Door Flex French Door Smart Refrigerator with AI Family Hub+ and AI Vision Inside - Stainless Steel",
            "sku": "6571681",
            "price": 3199.99,
            "savings": 100.0,
            "discount_percent": 3.1250097656555176,
            "priority_score": 399.3432526840545,
            "reviews": 162,
            "image_url": "images/6571681.jpg"
        },
        {
            "category": "Appliances",
            "title": "iRobot - Roomba 105 Combo Vac Robot Vacuum & Mop + AutoEmpty Dock - Black",
            "sku": "6618892",
            "price": 446.99,
            "savings": 77.0,
            "discount_percent": 17.22633615964563,
            "priority_score": 310.3155538496683,
            "reviews": 6,
            "image_url": "images/6618892.jpg"
        }
    ]
}